blackjackpy/__init__.py
blackjackpy/__main__.py
blackjackpy/blackjack.py
blackjackpy/py.typed
blackjackpy-0.3.0.dist-info/WHEEL
blackjackpy-0.3.0.dist-info/entry_points.txt
blackjackpy-0.3.0.dist-info/METADATA
blackjackpy-0.3.0.dist-info/RECORD
