Metadata-Version: 2.3
Name: blackjackpy
Version: 0.3.0
Summary: Blackjack game
Author: Saito Tsutomu
Author-email: Saito Tsutomu <tsutomu7@hotmail.co.jp>
License: Apache-2.0
Classifier: Development Status :: 1 - Planning
Classifier: License :: OSI Approved :: Apache Software License
Classifier: Programming Language :: Python
Classifier: Topic :: Software Development
Classifier: Topic :: Scientific/Engineering
Requires-Python: >=3.12
Project-URL: docs, https://saitotsutomu.github.io/blackjackpy/
Project-URL: homepage, https://github.com/SaitoTsutomu/blackjackpy
